pylexibench/__init__.py
pylexibench/__main__.py
pylexibench/dataset.py
pylexibench/matrix.py
pylexibench/repository.py
pylexibench/tree.py
pylexibench/util.py
pylexibench/wordlist.py
pylexibench/commands/__init__.py
pylexibench/commands/character_matrices.py
pylexibench/commands/cross_validation_data.py
pylexibench/commands/download.py
pylexibench/commands/glottolog_trees.py
pylexibench/commands/lingpy_cognates.py
pylexibench/commands/lingpy_wordlists.py
pylexibench/matrix_formats/__init__.py
pylexibench/matrix_formats/catg.py
pylexibench/matrix_formats/nexus.py
pylexibench/matrix_formats/phy.py
pylexibench-1.0.0.dist-info/LICENSE
pylexibench-1.0.0.dist-info/METADATA
pylexibench-1.0.0.dist-info/WHEEL
pylexibench-1.0.0.dist-info/entry_points.txt
pylexibench-1.0.0.dist-info/top_level.txt
pylexibench-1.0.0.dist-info/RECORD
