Metadata-Version: 2.2
Name: pylexibench
Version: 1.0.0
Summary: Benchmark Datasets for Computational Historical Linguistics
Home-page: https://codeberg.org/lexibank/pylexibench
Author: Johann-Mattis List, Luise Häuser and Robert Forkel
Author-email: mattis.list@lingpy.org
License: Apache 2.0
Project-URL: Bug Tracker, https://codeberg.org/lexibank/pylexibench/issues
Keywords: linguistics
Platform: any
Classifier: Intended Audience :: Developers
Classifier: Intended Audience :: Science/Research
Classifier: Natural Language :: English
Classifier: Operating System :: OS Independent
Classifier: Programming Language :: Python :: 3
Classifier: Programming Language :: Python :: 3.9
Classifier: Programming Language :: Python :: 3.10
Classifier: Programming Language :: Python :: 3.11
Classifier: Programming Language :: Python :: 3.12
Classifier: Programming Language :: Python :: 3.13
Classifier: Programming Language :: Python :: Implementation :: CPython
Classifier: Programming Language :: Python :: Implementation :: PyPy
Classifier: License :: OSI Approved :: Apache Software License
Requires-Python: >=3.9
License-File: LICENSE
Requires-Dist: clldutils>=3.24.2
Requires-Dist: nameparser
Requires-Dist: csvw
Requires-Dist: pycldf
Requires-Dist: cldfzenodo
Requires-Dist: cldfcatalog
Requires-Dist: lingpy[cluster]
Requires-Dist: commonnexus
Requires-Dist: pyglottolog
Requires-Dist: matplotlib
Provides-Extra: dev
Requires-Dist: flake8; extra == "dev"
Requires-Dist: wheel; extra == "dev"
Requires-Dist: twine; extra == "dev"
Requires-Dist: tox; extra == "dev"
Requires-Dist: build; extra == "dev"
Provides-Extra: test
Requires-Dist: pytest>=5; extra == "test"
Requires-Dist: pytest-mock; extra == "test"
Requires-Dist: pytest-cov; extra == "test"
